.gitignore
.travis.yml
CHANGELOG.md
LICENSE
README.md
config
nhlv
setup.py
mlbam/__init__.py
mlbam/auth.py
mlbam/nhlconfig.py
mlbam/nhlgamedata.py
mlbam/nhlsession.py
mlbam/nhlstream.py
mlbam/nhlv.py
mlbam/standings.py
mlbam/../README.md
mlbam/../config
mlbam/common/__init__.py
mlbam/common/config.py
mlbam/common/displayutil.py
mlbam/common/gamedata.py
mlbam/common/session.py
mlbam/common/stream.py
mlbam/common/util.py
nhlv.egg-info/PKG-INFO
nhlv.egg-info/SOURCES.txt
nhlv.egg-info/dependency_links.txt
nhlv.egg-info/entry_points.txt
nhlv.egg-info/requires.txt
nhlv.egg-info/top_level.txt
test/__init__.py
test/test_util.py