Metadata-Version: 2.1
Name: nhlv
Version: 0.0.1
Summary: Command-line interface to streaming NHL games (requires NHLV.tv subscription), game schedule and scores
Home-page: https://github.com/kmac/nhlv
License: GPLv3
Project-URL: Bug Reports, https://github.com/kmac/nhlv/issues
Project-URL: Source, https://github.com/kmac/nhlv
Platform: UNKNOWN
Classifier: Development Status :: 3 - Alpha
Classifier: Programming Language :: Python :: 3
Classifier: Environment :: Console
Classifier: License :: OSI Approved :: GNU General Public License v3 (GPLv3)
Classifier: Intended Audience :: End Users/Desktop
